[
    {
        "username": "admin",
        "password": "admin123"
    },
    {
        "username": "testuser",
        "password": "testpassword"
    },
    {
        "username": "user",
        "password": "user"
    },
    {
        "username": "wxy",
        "password": "123456"
    },
    {
        "username": "test",
        "password": "1234"
    },
    {
        "username": "video",
        "password": "123"
    },
    {
        "username": "demo",
        "password": "123"
    },
    {
        "username": "usr",
        "password": "123"
    }
]